{
  "generated_at": "2026-04-27T07:51:03Z",
  "subject": "FrankenPHP : L'observabilité passe à l'ère du temps réel avec Ember",
  "editorial": "Le paysage de FrankenPHP évolue à une vitesse fulgurante, mais un angle mort persistait souvent : l'observabilité granulaire et immédiate sans passer par une configuration digne de la NASA. Avec l'arrivée d'Ember, on franchit une étape cruciale vers une maturité industrielle pour cet environnement d'exécution moderne. Il ne s'agit plus seulement de servir du PHP rapidement via Go, mais de savoir précisément ce qui se passe sous le capot en temps réel.\n\nCe qui est fascinant ici, c'est l'exploitation native de l'API d'administration de Caddy. En se branchant directement sur le moteur, Ember élimine les couches d'abstraction inutiles qui ralentissent souvent le diagnostic en production. On voit émerger une tendance claire où les outils de développement cherchent à fusionner le monitoring système et le confort du terminal, offrant une visibilité que les logs textuels classiques ne peuvent tout simplement pas égaler.\n\nL'approche hybride choisie par Ember, proposant à la fois une interface terminal et une intégration Grafana, montre une compréhension fine des besoins actuels. D'un côté, le développeur a besoin d'une réponse instantanée lors du debugging local ou d'un déploiement à chaud. De l'autre, l'ingénieur DevOps nécessite des métriques persistantes pour analyser les tendances de performance sur le long terme. C'est cette dualité qui fait de l'outil un ajout indispensable à la stack.\n\nCette évolution confirme que PHP continue de se réinventer en s'appropriant les meilleurs concepts des écosystèmes Go et Rust. L'observabilité n'est plus une réflexion après-coup, mais un citoyen de première classe intégré nativement dans les serveurs d'application. Pour les praticiens, cela signifie moins de temps passé à déchiffrer des erreurs obscures et plus de temps à optimiser le code métier.\n\nÀ l'avenir, on peut s'attendre à ce que ce type d'outillage devienne la norme pour tous les serveurs d'application modernes. L'ère des fichiers de configuration statiques et des logs passifs touche à sa fin au profit de tableaux de bord interactifs et dynamiques. Si vous utilisez FrankenPHP, ignorer un tel niveau de visibilité serait une erreur stratégique pour la stabilité de vos applications.",
  "highlights": [
    {
      "title": "Ember : L'observabilité simplifiée pour FrankenPHP",
      "source_name": "Flux YoanDev",
      "source_url": "https://flux.yoandev.co/article/83c97a2cf847/",
      "analysis": "Ember change la donne pour les utilisateurs de FrankenPHP en transformant l'API d'administration de Caddy en un cockpit de pilotage visuel directement dans le terminal. Cette intégration permet une surveillance sans friction, réduisant drastiquement le temps moyen de résolution des incidents grâce à son interface intuitive. En combinant feedback immédiat et stockage de métriques via Grafana, l'outil s'adapte aussi bien au développement local qu'aux exigences de la production. C'est un pas de géant pour la fiabilité et la visibilité des infrastructures PHP modernes."
    }
  ],
  "resources": []
}